test
service_discovery
