Metadata-Version: 1.1
Name: microhackaton-service-discovery-py
Version: 0.0.4
Summary: A python package that works to provide service registration and discovery for http://microhackaton.github.io/2014/
Home-page: https://github.com/microhackaton/service-discovery-py
Author: Kamil Chmielewski
Author-email: kamil.chm@gmail.com
License: ASL 2.0
Keywords: kazoo service discovery zookeeper
Platform: UNKNOWN
Classifier: Development Status :: 3 - Alpha
Classifier: Topic :: Utilities
Classifier: License :: OSI Approved :: Apache Software License
Classifier: Operating System :: POSIX :: Linux
Classifier: Programming Language :: Python :: 2.7
